zLOG/EventLogger.py
zLOG/__init__.py
zLOG/tests/__init__.py
zLOG/tests/test_logging.py
zLOG/tests/testzLog.py
zLOG-3.1.dist-info/LICENSE.txt
zLOG-3.1.dist-info/METADATA
zLOG-3.1.dist-info/WHEEL
zLOG-3.1.dist-info/top_level.txt
zLOG-3.1.dist-info/RECORD
